swaggerpetstore/__init__.py
swaggerpetstore/api_helper.py
swaggerpetstore/configuration.py
swaggerpetstore/decorators.py
swaggerpetstore/swaggerpetstore_client.py
swaggerpetstore/controllers/__init__.py
swaggerpetstore/controllers/base_controller.py
swaggerpetstore/controllers/pet_controller.py
swaggerpetstore/controllers/store_controller.py
swaggerpetstore/controllers/user_controller.py
swaggerpetstore/exceptions/__init__.py
swaggerpetstore/exceptions/api_exception.py
swaggerpetstore/exceptions/o_auth_provider_exception.py
swaggerpetstore/http/__init__.py
swaggerpetstore/http/http_call_back.py
swaggerpetstore/http/http_client.py
swaggerpetstore/http/http_method_enum.py
swaggerpetstore/http/http_request.py
swaggerpetstore/http/http_response.py
swaggerpetstore/http/requests_client.py
swaggerpetstore/http/auth/__init__.py
swaggerpetstore/http/auth/custom_header_authentication.py
swaggerpetstore/models/__init__.py
swaggerpetstore/models/api_response.py
swaggerpetstore/models/category.py
swaggerpetstore/models/o_auth_provider_error_enum.py
swaggerpetstore/models/o_auth_scope_enum.py
swaggerpetstore/models/o_auth_token.py
swaggerpetstore/models/order.py
swaggerpetstore/models/pet.py
swaggerpetstore/models/status_1_enum.py
swaggerpetstore/models/status_2_enum.py
swaggerpetstore/models/status_enum.py
swaggerpetstore/models/tag.py
swaggerpetstore/models/user.py
swaggerpetstore/utilities/__init__.py
swaggerpetstore/utilities/file_wrapper.py
hamzaShoukatpy-2.0.dist-info/LICENSE
hamzaShoukatpy-2.0.dist-info/METADATA
hamzaShoukatpy-2.0.dist-info/WHEEL
hamzaShoukatpy-2.0.dist-info/top_level.txt
hamzaShoukatpy-2.0.dist-info/RECORD
